nitsm/__init__.py
nitsm/_pinmapinterfaces.py
nitsm/codemoduleapi.py
nitsm/debug.py
nitsm/enums.py
nitsm/pinquerycontexts.py
nitsm/tsmcontext.py
nitsm-0.2.0.dist-info/LICENSE
nitsm-0.2.0.dist-info/METADATA
nitsm-0.2.0.dist-info/WHEEL
nitsm-0.2.0.dist-info/top_level.txt
nitsm-0.2.0.dist-info/RECORD
