Metadata-Version: 2.1
Name: nitsm
Version: 0.2.0
Summary: NI TestStand Semiconductor Module Python API
Home-page: https://github.com/ni/nitsm-python
Author: NI
Author-email: opensource@ni.com
License: UNKNOWN
Platform: UNKNOWN
Classifier: License :: OSI Approved :: MIT License
Classifier: Operating System :: Microsoft :: Windows
Requires-Python: >=3.6
License-File: LICENSE
Requires-Dist: pywin32 (>=228) ; platform_system == "Windows"
